detect_indent/__init__.py
detect_indent/detect_indentation.py
detect_indent-1.0.0.dist-info/METADATA
detect_indent-1.0.0.dist-info/WHEEL
detect_indent-1.0.0.dist-info/top_level.txt
detect_indent-1.0.0.dist-info/RECORD
