Metadata-Version: 2.1
Name: detect-indent
Version: 1.0.0
Summary: Detects the indentation type and size of any string.
Author-email: Ethan Van Der Heijden <ethanvanderheijden@gmail.com>
Project-URL: Homepage, https://github.com/Ethan-Vanderheijden/detect-indent-py
Project-URL: Bug Tracker, https://github.com/Ethan-Vanderheijden/detect-indent-py/issues
Classifier: Programming Language :: Python :: 3
Classifier: License :: OSI Approved :: MIT License
Classifier: Operating System :: OS Independent
Requires-Python: >=3
